LICENSE
LICENSE.spdx
MANIFEST.in
README.rst
pyproject.toml
requirements.txt
setup.cfg
setup.py
pylibschc/__init__.py
pylibschc/_pydantic.py
pylibschc/clibschc.pxd
pylibschc/compressor.py
pylibschc/device.py
pylibschc/fragmenter.py
pylibschc/libschc.c
pylibschc/libschc.pyx
pylibschc/rules.py
pylibschc.egg-info/PKG-INFO
pylibschc.egg-info/SOURCES.txt
pylibschc.egg-info/dependency_links.txt
pylibschc.egg-info/requires.txt
pylibschc.egg-info/top_level.txt
src/mo.h
src/pylogging.c
src/pylogging.h
src/rules.c
src/rules.h
src/schc_config.h
src/libschc/bit_operations.c
src/libschc/bit_operations.h
src/libschc/compressor.c
src/libschc/compressor.h
src/libschc/fragmenter.c
src/libschc/fragmenter.h
src/libschc/jsmn.c
src/libschc/jsmn.h
src/libschc/picocoap.c
src/libschc/picocoap.h
src/libschc/schc.c
src/libschc/schc.h
src/libschc/schc_config_example.h
src/libschc/docs/rule_config.h
src/libschc/examples/timer.h
src/libschc/rules/rule_config_example.h
src/libschc/rules/rules_example.h
src/libschc/rules/rules_icmpv6.h
src/libschc/rules/rules_interop.h
src/libschc/rules/rules_lwm2m.h
src/libschc/rules/rules_pfw.h
src/rules/rule_config.h
tests/test_bitarray.py
tests/test_compressor.py
tests/test_debug.py
tests/test_device.py
tests/test_fragmenter.py
tests/test_rules.py