Metadata-Version: 2.1
Name: pylibschc
Version: 0.0.1b0
Summary: pylibschc - A python wrapper for libSCHC
Home-page: https://github.com/anr-bmbf-pivot/pylibschc
Download-URL: https://github.com/anr-bmbf-pivot/pylibschc
Author: Martine S. Lenders
Author-email: m.lenders@fu-berlin.de
License: GPLv3
Classifier: Development Status :: 4 - Beta
Classifier: License :: OSI Approved :: GNU General Public License v3 (GPLv3)
Classifier: Programming Language :: Python
Classifier: Programming Language :: Python :: 3
Classifier: Programming Language :: Python :: 3.7
Classifier: Programming Language :: Python :: 3.8
Classifier: Programming Language :: Python :: 3.9
Classifier: Programming Language :: Python :: 3.10
Classifier: Programming Language :: Python :: 3.11
Classifier: Intended Audience :: Developers
Classifier: Intended Audience :: Science/Research
Requires-Python: >=3.7
License-File: LICENSE
License-File: LICENSE.spdx
